lpi_prediction/__about__.py
lpi_prediction/__init__.py
lpi_prediction/lpi_data_encoder.py
lpi_prediction/lpi_data_provider.py
lpi_prediction/lpi_model.py
lpi_prediction/lpi_predictor.py
lpi_prediction-0.0.1.dist-info/LICENSE
lpi_prediction-0.0.1.dist-info/METADATA
lpi_prediction-0.0.1.dist-info/WHEEL
lpi_prediction-0.0.1.dist-info/top_level.txt
lpi_prediction-0.0.1.dist-info/RECORD
